sagemaker_data_insights/__init__.py
sagemaker_data_insights/analyze_feature.py
sagemaker_data_insights/analyze_target.py
sagemaker_data_insights/calc_stats_pandas_series.py
sagemaker_data_insights/categorical_utils.py
sagemaker_data_insights/const.py
sagemaker_data_insights/cross_column_stats.py
sagemaker_data_insights/histogram_functions.py
sagemaker_data_insights/insights.py
sagemaker_data_insights/model_utils.py
sagemaker_data_insights/spark_session.py
sagemaker_data_insights/text_utils.py
sagemaker_data_insights/visualize.py
sagemaker_data_insights/word_cloud.py
sagemaker_data_insights/xgboost_utils.py
sagemaker_data_insights/analyzers/__init__.py
sagemaker_data_insights/analyzers/binary_analyzer.py
sagemaker_data_insights/analyzers/categorical_analyzer.py
sagemaker_data_insights/analyzers/datetime_analyzer.py
sagemaker_data_insights/analyzers/feature_analyzer.py
sagemaker_data_insights/analyzers/numeric_analyzer.py
sagemaker_data_insights/analyzers/target_column_analyzer.py
sagemaker_data_insights/analyzers/text_analyzer.py
sagemaker_data_insights/analyzers/vector_analyzer.py
sagemaker_data_insights/analyzers/insights/__init__.py
sagemaker_data_insights/analyzers/insights/model_insights.py
sagemaker_data_insights/analyzers/insights/sklearn_utils.py
sagemaker_data_insights/analyzers/insights/utils.py
sagemaker_data_insights/analyzers/spark_engine/__init__.py
sagemaker_data_insights/analyzers/spark_engine/feature_analyzer.py
sagemaker_data_insights/analyzers/spark_engine/numeric_analyzer.py
sagemaker_data_insights/analyzers/spark_engine/string_analyzer.py
sagemaker_data_insights/column_data_insights/__init__.py
sagemaker_data_insights/column_data_insights/column_insights_data.py
sagemaker_data_insights/column_data_insights/constants.py
sagemaker_data_insights/column_data_insights/utils.py
sagemaker_data_insights/metrics/__init__.py
sagemaker_data_insights/metrics/metrics.py
sagemaker_data_insights/metrics/target_metrics.py
sagemaker_data_insights-0.4.0.dist-info/LICENSE
sagemaker_data_insights-0.4.0.dist-info/METADATA
sagemaker_data_insights-0.4.0.dist-info/NOTICE
sagemaker_data_insights-0.4.0.dist-info/WHEEL
sagemaker_data_insights-0.4.0.dist-info/top_level.txt
sagemaker_data_insights-0.4.0.dist-info/RECORD
